{
  "photos": [
    {
      "id": 1,
      "title": "Sunset at the Beach",
      "description": "Beautiful golden hour at Malibu Beach. The waves were perfect and the sky was painted with amazing colors.",
      "imageUrl": "/images/logo192.png",
      "location": "Malibu, CA",
      "date": "2024-01-15",
      "tags": ["sunset", "beach", "nature", "photography"],
      "category": "nature"
    },
    {
      "id": 2,
      "title": "Mountain Hiking",
      "description": "Reached the summit after 6 hours of hiking. The view was absolutely breathtaking and worth every step.",
      "imageUrl": "/images/logo192.png",
      "location": "Rocky Mountains, CO",
      "date": "2024-01-10",
      "tags": ["hiking", "mountains", "adventure", "nature"],
      "category": "adventure"
    },
    {
      "id": 3,
      "title": "City Lights",
      "description": "Night photography in downtown. The city never sleeps and the lights create such a magical atmosphere.",
      "imageUrl": "/images/logo192.png",
      "location": "Downtown, NY",
      "date": "2024-01-08",
      "tags": ["city", "night", "urban", "photography"],
      "category": "urban"
    },
    {
      "id": 4,
      "title": "Coffee Shop Vibes",
      "description": "Cozy morning at my favorite local coffee shop. The perfect spot for people watching and getting work done.",
      "imageUrl": "/images/logo192.png",
      "location": "Local Coffee Shop",
      "date": "2024-01-05",
      "tags": ["coffee", "lifestyle", "local", "morning"],
      "category": "lifestyle"
    },
    {
      "id": 5,
      "title": "Street Art",
      "description": "Amazing street art found while exploring the city. The creativity and talent of street artists always amazes me.",
      "imageUrl": "/images/logo192.png",
      "location": "Arts District, LA",
      "date": "2024-01-03",
      "tags": ["street art", "urban", "creativity", "culture"],
      "category": "art"
    },
    {
      "id": 6,
      "title": "Garden Flowers",
      "description": "Spring has arrived! These beautiful flowers are blooming in my backyard garden.",
      "imageUrl": "/images/logo192.png",
      "location": "Backyard Garden",
      "date": "2024-01-01",
      "tags": ["flowers", "spring", "garden", "nature"],
      "category": "nature"
    },
    {
      "id": 7,
      "title": "Tech Meetup",
      "description": "Great networking event with fellow developers. Always inspiring to meet people who share the same passion for technology.",
      "imageUrl": "/images/logo192.png",
      "location": "Tech Hub, SF",
      "date": "2023-12-28",
      "tags": ["tech", "networking", "community", "development"],
      "category": "tech"
    },
    {
      "id": 8,
      "title": "Road Trip",
      "description": "Epic road trip across the country. The open road, good music, and amazing landscapes made for unforgettable memories.",
      "imageUrl": "/images/logo192.png",
      "location": "Highway 1, CA",
      "date": "2023-12-20",
      "tags": ["road trip", "travel", "adventure", "freedom"],
      "category": "adventure"
    }
  ],
  "categories": [
    { "key": "all", "label": "All Photos" },
    { "key": "nature", "label": "Nature" },
    { "key": "adventure", "label": "Adventure" },
    { "key": "urban", "label": "Urban" },
    { "key": "lifestyle", "label": "Lifestyle" },
    { "key": "art", "label": "Art" },
    { "key": "tech", "label": "Technology" }
  ]
}
